{
  "id": "aries_horoscope_for_may_04May2026",
  "category": "Horoscope",
  "telugu_title": "మేష రాశి దినఫలాలు - మే 4, 2026: ఆర్థిక లావాదేవీలు మరియు రుణాలకు అనుకూల సమయం",
  "summary_short": "మేష రాశి వారికి ఈ రోజు రుణ మరియు ఆర్థిక వ్యవహారాలకు అనుకూలమైన రోజు. సరైన పత్రాలతో ముందుకు వెళితే మంచి ఫలితాలు వస్తాయి.",
  "voiceover_script": "మేష రాశి వారికి ఈ రోజు ఆర్థికంగా అద్భుతంగా ఉండబోతోంది. లోన్స్ లేదా క్రెడిట్ పనుల్లో విజయం ఖాయం. పూర్తి వివరాల కోసం వీడియో చూడండి!",
  "poster_content": "మేష రాశి వారికి ఈ రోజు (మే 4, 2026) ఎలా ఉంటుంది?\nఈ రోజు ఆర్థిక వ్యవహారాలు, లోన్ లేదా క్రెడిట్ పనులకు చాలా అనుకూలమైనది. సరైన పత్రాలతో ముందుకు వెళితే విజయం మీదే.\n\nకెరీర్ మరియు వ్యక్తిగత వికాసం\nఆఫీసులో మీ పనులను గడువు లోపు పూర్తి చేయడానికి కష్టపడతారు. శ్రమకు తగిన గుర్తింపు లభిస్తుంది.\n\nకుటుంబం మరియు సంబంధాలు\nకుటుంబ సభ్యులతో ఆర్థిక విషయాలపై చర్చలు జరుపుతారు. వారి మద్దతు మీకు లభిస్తుంది.\n\nఅదృష్ట రంగు: ఎరుపు\nఅదృష్ట సంఖ్య: 9\nసూచన: మీ ముఖ్యమైన పత్రాలను జాగ్రత్తగా చూసుకోండి.",
  "blog_content": "<p>మేష రాశి వారికి ఈ రోజు ఆర్థిక పరంగా చాలా కీలకమైనది. మీరు అదనపు క్రెడిట్, మార్టిగేజ్ లేదా లోన్ కోసం ప్రయత్నిస్తున్నట్లయితే, మీ డాక్యుమెంట్లు అన్నీ సిద్ధంగా ఉంచుకుంటే ఇది సరైన సమయం.</p><p>గడువు లోపు పనులు పూర్తి చేయడానికి చివరి నిమిషంలో కొన్ని వివరాల కోసం మీరు కొద్దిగా కష్టపడాల్సి రావచ్చు. అయినప్పటికీ, ఈ రోజు మీ ప్రయత్నాలకు అద్భుతమైన ఫలితాలు వచ్చే అవకాశం ఉంది. మీ పత్రాలను జాగ్రత్తగా చూసుకోండి మరియు ఆత్మవిశ్వాసంతో ముందుకు సాగండి.</p>",
  "youtube_metadata": {
    "title": "మేష రాశి దినఫలాలు - మే 4, 2026 | Aries Daily Horoscope Today in Telugu",
    "description": "మేష రాశి వారికి మే 4, 2026 న ఎలా ఉండబోతోంది? ఆర్థిక విషయాలు, లోన్స్ మరియు కెరీర్ పరంగా తీసుకోవాల్సిన జాగ్రత్తలు ఏమిటి? పూర్తి వివరాలు ఈ వీడియోలో చూడండి. మరిన్ని రాశి ఫలాల కోసం మా ఛానెల్ ను సబ్స్క్రైబ్ చేసుకోండి.",
    "tags": [
      "Mesha Rasi",
      "Aries Horoscope Telugu",
      "Daily Horoscope Telugu",
      "May 4 2026 Horoscope",
      "Telugu Rasi Phalalu",
      "Mesha Rasi Today",
      "Astrology Telugu"
    ]
  },
  "seo": {
    "title": "మేష రాశి దినఫలాలు - మే 4, 2026 | Aries Horoscope in Telugu",
    "description": "మేష రాశి వారికి మే 4, 2026 న ఆర్థిక విషయాలు, లోన్స్ మరియు కెరీర్ పరంగా అద్భుతమైన అవకాశాలు ఉన్నాయి. పూర్తి రాశి ఫలాలు చదవండి.",
    "keywords": [
      "Mesha rasi phalalu",
      "Aries horoscope today telugu",
      "Telugu astrology",
      "May 4 2026 rasi phalalu"
    ]
  },
  "media": {
    "featured_image": "images/aries_horoscope_for_may_04May2026.webp",
    "poster_9_16": "posters/aries_horoscope_for_may_04May2026_poster.jpg",
    "voiceover_audio": "audio/aries_horoscope_for_may_04May2026.mp3",
    "video_reel": "videos/aries_horoscope_for_may_04May2026.mp4"
  },
  "source": {
    "original_url": "https://horoscopes.e-tarocchi.com/aries-tomorrow.html",
    "original_title": "Aries Tomorrow Horoscope",
    "date": "03/05/2026"
  },
  "published_date": "03/05/2026",
  "date": "03/05/2026"
}