{
  "id": "aries_horoscope_for_april_25Apr2026",
  "category": "Prediction",
  "telugu_title": "మేష రాశి దిన ఫలాలు - ఏప్రిల్ 25, 2026: వృత్తిలో అద్భుత విజయాలు",
  "summary_short": "మేష రాశి వారికి ఈ రోజు వృత్తిపరంగా అద్భుతమైన గుర్తింపు లభిస్తుంది. కీర్తి ప్రతిష్టలు పెరుగుతాయి, అలాగే పనిలో బాధ్యతలు కూడా అధికమవుతాయి.",
  "voiceover_script": "మేష రాశి వారికి ఈ రోజు అద్భుతంగా ఉండబోతోంది, కెరీర్‌లో మంచి గుర్తింపు లభిస్తుంది. పూర్తి వివరాలు మరియు అదృష్ట సంఖ్య కోసం ఈ వీడియో చూడండి!",
  "poster_content": "మేష రాశి వారికి ఈ రోజు (ఏప్రిల్ 25, 2026) ఎలా ఉంటుంది? - ఈ రోజు మీరు పనిచేసే చోట విశేషమైన గుర్తింపు పొందుతారు. మీలో దాగి ఉన్న ప్రతిభను అందరూ గుర్తిస్తారు. - కెరీర్ మరియు వ్యక్తిగత వికాసం: వృత్తిపరంగా అద్భుతమైన రోజు. అధికారుల మన్ననలు పొందుతారు. పనిభారం పెరిగినా సమర్థవంతంగా పూర్తి చేస్తారు. - కుటుంబం మరియు సంబంధాలు: మీ కీర్తి, సంతోషం కుటుంబ వాతావరణాన్ని ఉల్లాసంగా మారుస్తాయి. బంధుమిత్రులతో బిజీగా గడుపుతారు. - అదృష్ట రంగు: ఎరుపు. - అదృష్ట సంఖ్య: 9. - సూచన: పెరుగుతున్న బాధ్యతలకు అనుగుణంగా సమయాన్ని ప్లాన్ చేసుకోండి.",
  "blog_content": "<h2>మేష రాశి దిన ఫలాలు - ఏప్రిల్ 25, 2026</h2><p>ఈ రోజు మేష రాశి వారికి వృత్తి, వ్యక్తిగత జీవితంలో అద్భుతమైన ఫలితాలు రానున్నాయి. మీరు పనిచేసే చోట మీ పై అధికారుల వద్ద మంచి గుర్తింపు పొందుతారు.</p><h3>కెరీర్ మరియు వృత్తి జీవితం</h3><p>మీ సహోద్యోగులు ఇంతకు ముందు గమనించని మీలోని కొత్త కోణాలను మరియు నైపుణ్యాలను గుర్తిస్తారు. మీ కీర్తి ప్రతిష్టలు పెరిగే సమయం ఇది. వృత్తిపరంగా మీరు వేసే అడుగులు విజయవంతం అవుతాయి.</p><h3>సామాజిక మరియు వ్యక్తిగత జీవితం</h3><p>సంతోషం మరియు జనాదరణ పెరిగే కొద్దీ, మీపై బాధ్యతలు కూడా పెరుగుతాయి. ఈ విషయాన్ని ఎల్లప్పుడూ గుర్తుంచుకోండి. రాబోయే రోజుల్లో మీరు వివిధ కార్యక్రమాలు, బాధ్యతలతో చాలా బిజీగా గడపబోతున్నారు. సమయాన్ని సద్వినియోగం చేసుకోండి.</p>",
  "youtube_metadata": {
    "title": "మేష రాశి దిన ఫలాలు - ఏప్రిల్ 25, 2026 | Aries Daily Horoscope Telugu",
    "description": "మేష రాశి దిన ఫలాలు - ఏప్రిల్ 25, 2026. ఈ రోజు మేష రాశి వారికి ఎలా ఉండబోతోంది? కెరీర్, కుటుంబం, అదృష్ట రంగు మరియు సంఖ్యల గురించి పూర్తి వివరాలు తెలుసుకోండి. Aries daily horoscope in Telugu.",
    "tags": [
      "మేష రాశి",
      "Aries Horoscope Telugu",
      "Daily Horoscope Telugu",
      "ఏప్రిల్ 25 2026 రాశి ఫలాలు",
      "Mesha Rasi",
      "Astrology Telugu",
      "Today Horoscope Telugu"
    ]
  },
  "seo": {
    "title": "మేష రాశి దిన ఫలాలు - ఏప్రిల్ 25, 2026 | Aries Horoscope in Telugu",
    "description": "మేష రాశి దిన ఫలాలు - ఏప్రిల్ 25, 2026. ఈ రోజు మేష రాశి వారి కెరీర్, కుటుంబం మరియు ఆర్థిక స్థితిగతుల గురించి పూర్తి వివరాలు.",
    "keywords": [
      "Mesha rasi",
      "Aries daily horoscope Telugu",
      "April 25 2026 horoscope",
      "Astrology in Telugu",
      "మేష రాశి ఫలాలు"
    ]
  },
  "media": {
    "featured_image": "images/aries_horoscope_for_april_25Apr2026.webp",
    "poster_9_16": "posters/aries_horoscope_for_april_25Apr2026_poster.jpg",
    "voiceover_audio": "audio/aries_horoscope_for_april_25Apr2026.mp3",
    "video_reel": "videos/aries_horoscope_for_april_25Apr2026.mp4"
  },
  "source": {
    "original_url": "https://horoscopes.e-tarocchi.com/aries-tomorrow.html",
    "original_title": "Aries Tomorrow Horoscope",
    "date": "24/04/2026"
  },
  "published_date": "24/04/2026",
  "date": "24/04/2026"
}