{
  "id": "it_rules_india_proposes_new_digital_rules_to_regulate_news_and_political_posts_on_social_media_bbc",
  "category": "జాతీయ వార్తలు",
  "telugu_title": "సోషల్ మీడియాలో వార్తలు, రాజకీయ పోస్టుల నియంత్రణకు కేంద్రం కొత్త ఐటీ నిబంధనలు!",
  "summary_short": "సోషల్ మీడియాలో ఫేక్ న్యూస్, రాజకీయ పోస్టులను కట్టడి చేసేందుకు భారత ప్రభుత్వం కొత్త ఐటీ నిబంధనలను ప్రతిపాదించింది.",
  "voiceover_script": "సోషల్ మీడియాలో రాజకీయ పోస్టులు, వార్తల నియంత్రణకు కేంద్రం కొత్త ఐటీ రూల్స్ తీసుకురాబోతోంది. తప్పుడు వార్తలకు చెక్ పెట్టడమే లక్ష్యం! పూర్తి వివరాలు వీడియోలో.",
  "poster_content": "సోషల్ మీడియాలో రాజకీయ పోస్టుల నియంత్రణకు కేంద్రం సన్నాహాలు. ఫేక్ న్యూస్, రెచ్చగొట్టే రాజకీయ కంటెంట్ కట్టడి కోసం కొత్త డిజిటల్ నిబంధనల (IT Rules) ప్రతిపాదన. సోషల్ మీడియా సంస్థలపై మరింత బాధ్యత.",
  "blog_content": "<h1>సోషల్ మీడియాలో వార్తలు, రాజకీయ పోస్టుల నియంత్రణకు నూతన ఐటీ నిబంధనలు</h1><p>భారత ప్రభుత్వం సోషల్ మీడియా ప్లాట్‌ఫారమ్‌లలో వార్తలు మరియు రాజకీయ కంటెంట్‌ను నియంత్రించే దిశగా కీలక అడుగులు వేస్తోంది. సోషల్ మీడియాలో తప్పుడు వార్తలు మరియు రెచ్చగొట్టే రాజకీయ పోస్టులకు అడ్డుకట్ట వేయడానికి కొత్త డిజిటల్ నిబంధనలను (IT Rules) ప్రతిపాదించింది.</p><p>ఈ కొత్త నిబంధనల ప్రకారం, సోషల్ మీడియా సంస్థలు ఫేక్ న్యూస్ మరియు రాజకీయపరమైన తప్పుడు సమాచారాన్ని వేగంగా తొలగించాల్సి ఉంటుంది. బీబీసీ నివేదిక ప్రకారం, ఈ ముసాయిదా నిబంధనలు డిజిటల్ మీడియా ప్లాట్‌ఫారమ్‌లపై మరింత బాధ్యతను మోపనున్నాయి. పౌరుల సమాచార భద్రత మరియు జాతీయ భద్రత దృష్ట్యా ఈ చర్యలు తీసుకుంటున్నట్లు తెలుస్తోంది.</p>",
  "youtube_metadata": {
    "title": "సోషల్ మీడియా యూజర్లకు అలర్ట్: కేంద్రం కొత్త ఐటీ రూల్స్ | India Proposes New IT Rules For Social Media",
    "description": "సోషల్ మీడియాలో ఫేక్ న్యూస్ మరియు రాజకీయ పోస్టులను నియంత్రించేందుకు భారత ప్రభుత్వం కొత్త డిజిటల్ నిబంధనలను ప్రతిపాదించింది. ఈ కొత్త ఐటీ రూల్స్ (IT Rules) గురించి బీబీసీ నివేదించిన పూర్తి వివరాలు ఈ వీడియోలో తెలుసుకోండి. లైక్ చేయండి, షేర్ చేయండి మరియు సబ్‌స్క్రైబ్ చేసుకోండి!",
    "tags": [
      "New IT Rules India",
      "Social Media Guidelines Telugu",
      "Fake News Control India",
      "Political Posts Social Media",
      "Telugu News Updates",
      "Central Govt New Rules",
      "Digital India"
    ]
  },
  "seo": {
    "title": "సోషల్ మీడియాలో రాజకీయ పోస్టుల నియంత్రణకు కేంద్రం కొత్త ఐటీ నిబంధనలు | New IT Rules in India",
    "description": "సోషల్ మీడియాలో ఫేక్ న్యూస్, రాజకీయ పోస్టులను కట్టడి చేసేందుకు భారత ప్రభుత్వం ప్రతిపాదించిన కొత్త ఐటీ (IT) నిబంధనల గురించి పూర్తి వివరాలు.",
    "keywords": [
      "IT rules India",
      "Social media regulation",
      "New digital rules Telugu",
      "Fake news control",
      "Indian government IT rules"
    ]
  },
  "media": {
    "featured_image": "images/it_rules_india_proposes_new_digital_rules_to_regulate_news_and_political_posts_on_social_media_bbc.webp",
    "poster_9_16": "posters/it_rules_india_proposes_new_digital_rules_to_regulate_news_and_political_posts_on_social_media_bbc_poster.jpg",
    "voiceover_audio": "audio/it_rules_india_proposes_new_digital_rules_to_regulate_news_and_political_posts_on_social_media_bbc.mp3",
    "video_reel": "videos/it_rules_india_proposes_new_digital_rules_to_regulate_news_and_political_posts_on_social_media_bbc.mp4"
  },
  "source": {
    "original_url": "https://news.google.com/rss/articles/CBMiWkFVX3lxTE51RGtNb0xCUXNueGdvTnQweHBRZi1RdXBRZF9SV3V3REVWU0xic0Q0S3RwVUhXcGtxWWtZUEZTZ1ZvaG5WWkYyNE5HcWFxLWxyOXNBN0pzeEtfUQ?oc=5",
    "original_title": "IT rules: India proposes new digital rules to regulate news and political posts on social media - BBC",
    "date": "2026-04-10 00:23:18"
  }
}