{
  "id": "libra_horoscope_for_may_04May2026",
  "category": "Horoscope",
  "telugu_title": "తులా రాశి దినఫలాలు - మే 4, 2026: ప్రాజెక్ట్‌ల నిర్వహణలో సవాళ్లు మరియు ఆధారాలు!",
  "summary_short": "తులా రాశి వారికి ఈ రోజు ప్రాజెక్టుల నిర్వహణ సవాలుగా మారుతుంది. కేవలం అభిప్రాయాల కంటే ఆధారాలు మరియు ఆచరణాత్మక విలువకు ప్రాధాన్యత ఇవ్వాలి.",
  "voiceover_script": "తులా రాశి వారికి ఈ రోజు చాలా కీలకం! ప్రాజెక్ట్ నిర్వహణలో సవాళ్లు ఎదురవుతాయి, వాస్తవాలకు మాత్రమే ప్రాధాన్యత ఇవ్వండి. పూర్తి వివరాల కోసం వీడియో చూడండి!",
  "poster_content": "తులా రాశి వారికి ఈ రోజు (మే 4, 2026) ఎలా ఉంటుంది? ఈ రోజు ప్రాజెక్ట్‌లు మరియు వ్యక్తులను ఎలా నిర్వహించాలో తెలుసుకోవడం ఒక సవాలుగా మారుతుంది. కేవలం అభిప్రాయాలు సరిపోవు, ఆధారాలు మరియు ఆచరణాత్మక విలువ ఉండాలి. కెరీర్ మరియు వ్యక్తిగత వికాసం: పని ప్రదేశంలో నిర్ణయాలకు ఖచ్చితమైన ఆధారాలు అవసరం. ఆచరణాత్మక ఆలోచనలతో ముందుకు సాగండి. కుటుంబం మరియు సంబంధాలు: కుటుంబ సభ్యులతో వాస్తవాల ఆధారంగా మాట్లాడండి, అపార్థాలకు తావివ్వకండి. అదృష్ట రంగు: తెలుపు. అదృష్ట సంఖ్య: 6. సూచన: ఊహాగానాల కంటే వాస్తవాలను నమ్మండి.",
  "blog_content": "<article><h2>తులా రాశి దినఫలాలు - మే 4, 2026</h2><p>ఈ రోజు తులా రాశి వారికి ప్రాజెక్ట్‌లు మరియు వ్యక్తులను ఎలా నిర్వహించాలో తెలుసుకోవడం ఒక ప్రత్యేక ఆసక్తిగా మరియు సవాలుగా మారుతుంది. కేవలం అభిప్రాయాలు మాత్రమే ఇప్పుడు మీకు సరిపోవు; వాటికి ఖచ్చితమైన ఆధారాలు లేదా అధికారిక మద్దతు ఉండాలి. అన్నింటికంటే ముఖ్యంగా, అవి ఆచరణాత్మక విలువను మరియు ప్రయోజనాన్ని కలిగి ఉండాలి.</p><h3>కెరీర్ మరియు వృత్తి</h3><p>పని ప్రదేశంలో మీరు తీసుకునే నిర్ణయాలకు ఆధారాలు అవసరం. గాలి కబుర్లను నమ్మకండి, ప్రతి విషయాన్ని లోతుగా విశ్లేషించి ఆచరణలో పెట్టండి.</p><h3>వ్యక్తిగత జీవితం</h3><p>కుటుంబంలో లేదా స్నేహితులతో మాట్లాడేటప్పుడు స్పష్టత మరియు వాస్తవాల ఆధారంగా వ్యవహరించడం మీకు మేలు చేస్తుంది. ఊహాగానాలకు దూరంగా ఉండండి.</p></article>",
  "youtube_metadata": {
    "title": "తులా రాశి దినఫలాలు - మే 4, 2026 | Tula Rasi Phalalu Today | Daily Horoscope",
    "description": "మే 4, 2026 న తులా రాశి వారి దినఫలాలు. ఈ రోజు ప్రాజెక్ట్‌ల నిర్వహణ, కెరీర్ సవాళ్లు మరియు వ్యక్తిగత జీవితం ఎలా ఉండబోతోందో తెలుసుకోండి. వాస్తవాలకు ప్రాధాన్యత ఇవ్వాల్సిన సమయం. మరిన్ని రాశి ఫలాల కోసం మా ఛానెల్‌ను సబ్‌స్క్రైబ్ చేసుకోండి.",
    "tags": [
      "Tula rasi phalalu",
      "Libra horoscope telugu",
      "Daily horoscope telugu",
      "మే 4 2026 రాశి ఫలాలు",
      "Tula rasi today",
      "Telugu astrology"
    ]
  },
  "seo": {
    "title": "తులా రాశి దినఫలాలు - మే 4, 2026 | Libra Daily Horoscope in Telugu",
    "description": "తులా రాశి దినఫలాలు మే 4, 2026. ఈ రోజు తులా రాశి వారి కెరీర్, కుటుంబం, అదృష్ట రంగు మరియు సంఖ్య గురించి పూర్తి వివరాలు తెలుసుకోండి.",
    "keywords": [
      "Tula rasi",
      "Libra daily horoscope",
      "Telugu astrology",
      "May 4 2026 horoscope",
      "Tula rasi today"
    ]
  },
  "media": {
    "featured_image": "images/libra_horoscope_for_may_04May2026.webp",
    "poster_9_16": "posters/libra_horoscope_for_may_04May2026_poster.jpg",
    "voiceover_audio": "audio/libra_horoscope_for_may_04May2026.mp3",
    "video_reel": "videos/libra_horoscope_for_may_04May2026.mp4"
  },
  "source": {
    "original_url": "https://horoscopes.e-tarocchi.com/libra-tomorrow.html",
    "original_title": "Libra Tomorrow Horoscope",
    "date": "03/05/2026"
  },
  "published_date": "03/05/2026",
  "date": "03/05/2026"
}