{
  "id": "virgo_horoscope_for_april_22Apr2026",
  "category": "Horoscope",
  "telugu_title": "కన్యా రాశి దిన ఫలాలు - ఏప్రిల్ 22, 2026",
  "summary_short": "కన్యా రాశి వారు ఈ రోజు చిన్న వివరాలను వదిలేసి, ప్రధాన విషయాలపై దృష్టి పెట్టాలి. భావోద్వేగాలు ఉప్పొంగుతాయి.",
  "voiceover_script": "కన్యా రాశి వారికి ఈ రోజు అద్భుతంగా ఉండబోతోంది! ప్రధాన విషయాలపై దృష్టి పెట్టండి, మనసు ఆనందంతో ఉప్పొంగుతుంది. పూర్తి వివరాలు ఇక్కడ చూడండి!",
  "poster_content": "కన్యా రాశి వారికి ఈ రోజు (ఏప్రిల్ 22, 2026) ఎలా ఉంటుంది? ఈ రోజు మీరు చిన్న వివరాలను వదిలేసి, ప్రధాన విషయాలపై దృష్టి పెట్టాలి. భావోద్వేగాలు ఉప్పొంగుతాయి. కెరీర్ మరియు వ్యక్తిగత వికాసం: వృత్తిలో మూల సూత్రాలను గ్రహించడం ద్వారా పనులు సులభంగా పూర్తి చేస్తారు. కుటుంబం మరియు సంబంధాలు: కుటుంబ సభ్యుల పట్ల ప్రేమ పెరుగుతుంది, బంధాలు బలపడతాయి. అదృష్ట రంగు: ఆకుపచ్చ. అదృష్ట సంఖ్య: 5. సూచన: అనవసరమైన వివరాల గురించి ఆలోచించకండి.",
  "blog_content": "<div><p><strong>కన్యా రాశి (ఏప్రిల్ 22, 2026):</strong> ఈ రోజు మీకు విషయాలను విస్తృతంగా అర్థం చేసుకోవడం చాలా సులభం అవుతుంది. చిన్న చిన్న వివరాల గురించి ఎక్కువగా ఆలోచించకండి, వాటి కోసం తర్వాత సమయం కేటాయించవచ్చు.</p><p>ముందుగా అసలు విషయాన్ని లేదా మూల సూత్రాన్ని గ్రహిస్తే, భవిష్యత్తులో మిగతావి వాటంతట అవే అర్థమవుతాయి. ఇలా చేయడం వల్ల మీ పనులు చాలా సులభతరం అవుతాయి. భావోద్వేగాలు పెరుగుతాయి, మీ మనసు ఉప్పొంగుతుంది. ఇతరుల పట్ల ప్రేమ, దయ చూపిస్తారు.</p></div>",
  "youtube_metadata": {
    "title": "కన్యా రాశి దిన ఫలాలు - ఏప్రిల్ 22, 2026 | Virgo Daily Horoscope Today",
    "description": "కన్యా రాశి దిన ఫలాలు ఏప్రిల్ 22, 2026. ఈ రోజు కన్యా రాశి వారి కెరీర్, ఆరోగ్యం, కుటుంబం మరియు ఆర్థిక పరిస్థితులు ఎలా ఉన్నాయో తెలుసుకోండి. జ్యోతిష్య నివారణలు మరియు అదృష్ట సంఖ్యల కోసం వీడియోను పూర్తిగా చూడండి.",
    "tags": [
      "Virgo Horoscope Telugu",
      "Kanya Rasi Phalalu",
      "Daily Horoscope Telugu",
      "April 22 2026 Horoscope",
      "Telugu Astrology",
      "Kanya Rasi Today"
    ]
  },
  "seo": {
    "title": "కన్యా రాశి దిన ఫలాలు ఏప్రిల్ 22, 2026 | Virgo Horoscope in Telugu",
    "description": "ఏప్రిల్ 22, 2026 కన్యా రాశి దిన ఫలాలు. ఈ రోజు కన్యా రాశి వారి ఆరోగ్య, ఆర్థిక, కుటుంబ మరియు వృత్తి సంబంధిత విషయాలు ఇక్కడ చదవండి.",
    "keywords": [
      "Virgo horoscope telugu",
      "Kanya rasi phalalu today",
      "Telugu astrology",
      "April 22 2026 horoscope"
    ]
  },
  "media": {
    "featured_image": "images/virgo_horoscope_for_april_22Apr2026.webp",
    "poster_9_16": "posters/virgo_horoscope_for_april_22Apr2026_poster.jpg",
    "voiceover_audio": "audio/virgo_horoscope_for_april_22Apr2026.mp3",
    "video_reel": "videos/virgo_horoscope_for_april_22Apr2026.mp4"
  },
  "source": {
    "original_url": "https://horoscopes.e-tarocchi.com/virgo-tomorrow.html",
    "original_title": "Virgo Tomorrow Horoscope",
    "date": "21/04/2026"
  },
  "published_date": "21/04/2026",
  "date": "21/04/2026"
}